setup.py
hilltoppy/__init__.py
hilltoppy/com.py
hilltoppy/hilltop.py
hilltoppy/mountain_top.py
hilltoppy/utils.py
hilltoppy/web_service.py
sphinx/source/conf.py
hilltop_py-2.3.1.dist-info/METADATA
hilltop_py-2.3.1.dist-info/WHEEL
hilltop_py-2.3.1.dist-info/licenses/LICENSE.txt
hilltop_py-2.3.1.dist-info/RECORD
